README.md
setup.py
structout/__init__.py
structout/__version__.py
structout/graph.py
structout/heatmap.py
structout/intlist.py
structout/intlistV2.py
structout/rnagraph.py
structout.egg-info/PKG-INFO
structout.egg-info/SOURCES.txt
structout.egg-info/dependency_links.txt
structout.egg-info/requires.txt
structout.egg-info/top_level.txt