Metadata-Version: 2.1
Name: structout
Version: 0.1.51
Summary: pretty print data structures
Home-page: https://github.com/smautner/StructOut_py3
Author: Stefan Mautner
Author-email: myl4stn4m3@cs.uni-freiburg.de
License: GPLv3
Requires-Python: >=3.8
